prefetch_plus/prefetch_plus.py
prefetch_plus/__init__.py
django_prefetch_plus-0.3.3.dist-info/METADATA
django_prefetch_plus-0.3.3.dist-info/top_level.txt
django_prefetch_plus-0.3.3.dist-info/metadata.json
django_prefetch_plus-0.3.3.dist-info/WHEEL
django_prefetch_plus-0.3.3.dist-info/DESCRIPTION.rst
django_prefetch_plus-0.3.3.dist-info/RECORD
